{
  "Name": "MECBL_spm_low_1_A_sup_35",
  "GeneralInformation": {
    "ID": "string",
    "Description": "string",
    "Building type": "string",
    "Roof Shape": "string",
    "Roof Cover Type": "string",
    "Roof Cover Quality": "string",
    "Roof Deck Attachment": "string",
    "Roof-Wall Connection": "string",
    "Secondary Water Resistance": "bool",
    "Garage": "string",
    "Shutters": "bool",
    "Terrain": "string"
  },
  "EDP": {
    "Type": "Peak Gust Wind Speed",
    "Unit": [
      1.0,
      "mph"
    ]
  },
  "DSGroups": [
    {
      "MedianEDP": 126.36840701414488,
      "Beta": 0.16669948742281124,
      "CurveType": "LogNormal",
      "DSGroupType": "Single",
      "DamageStates": [
        {
          "Weight": 1.0,
          "Consequences": {
            "ReconstructionCost": {
              "Amount": 0.04708946798697859
            }
          },
          "Description": "Minor"
        }
      ]
    },
    {
      "MedianEDP": 138.0385118932309,
      "Beta": 0.14110932130958306,
      "CurveType": "LogNormal",
      "DSGroupType": "Single",
      "DamageStates": [
        {
          "Weight": 1.0,
          "Consequences": {
            "ReconstructionCost": {
              "Amount": 0.09489173726213057
            }
          },
          "Description": "Moderate"
        }
      ]
    },
    {
      "MedianEDP": 157.42840756560796,
      "Beta": 0.14595439379809247,
      "CurveType": "LogNormal",
      "DSGroupType": "Single",
      "DamageStates": [
        {
          "Weight": 1.0,
          "Consequences": {
            "ReconstructionCost": {
              "Amount": 0.220127117318817
            }
          },
          "Description": "Severe"
        }
      ]
    },
    {
      "MedianEDP": 225.88919060705598,
      "Beta": 0.12769334905918084,
      "CurveType": "LogNormal",
      "DSGroupType": "Single",
      "DamageStates": [
        {
          "Weight": 1.0,
          "Consequences": {
            "ReconstructionCost": {
              "Amount": 0.7612026101461005
            }
          },
          "Description": "Destruction"
        }
      ]
    }
  ]
}