{
  "Name": "MERBH_spm_med_1_A_sup_100",
  "GeneralInformation": {
    "ID": "string",
    "Description": "string",
    "Building type": "string",
    "Roof Shape": "string",
    "Roof Cover Type": "string",
    "Roof Cover Quality": "string",
    "Roof Deck Attachment": "string",
    "Roof-Wall Connection": "string",
    "Secondary Water Resistance": "bool",
    "Garage": "string",
    "Shutters": "bool",
    "Terrain": "string"
  },
  "EDP": {
    "Type": "Peak Gust Wind Speed",
    "Unit": [
      1.0,
      "mph"
    ]
  },
  "DSGroups": [
    {
      "MedianEDP": 95.31686197741277,
      "Beta": 0.18642701112026772,
      "CurveType": "LogNormal",
      "DSGroupType": "Single",
      "DamageStates": [
        {
          "Weight": 1.0,
          "Consequences": {
            "ReconstructionCost": {
              "Amount": 0.022265875748700342
            }
          },
          "Description": "Minor"
        }
      ]
    },
    {
      "MedianEDP": 100.901065013455,
      "Beta": 0.1589512415046359,
      "CurveType": "LogNormal",
      "DSGroupType": "Single",
      "DamageStates": [
        {
          "Weight": 1.0,
          "Consequences": {
            "ReconstructionCost": {
              "Amount": 0.030274385636811754
            }
          },
          "Description": "Moderate"
        }
      ]
    },
    {
      "MedianEDP": 178.57470754052605,
      "Beta": 0.11537224026222465,
      "CurveType": "LogNormal",
      "DSGroupType": "Single",
      "DamageStates": [
        {
          "Weight": 1.0,
          "Consequences": {
            "ReconstructionCost": {
              "Amount": 0.29099563647583515
            }
          },
          "Description": "Severe"
        }
      ]
    },
    {
      "MedianEDP": 5878.438122981516,
      "Beta": 0.08250000000000013,
      "CurveType": "LogNormal",
      "DSGroupType": "Single",
      "DamageStates": [
        {
          "Weight": 1.0,
          "Consequences": {
            "ReconstructionCost": {
              "Amount": 0.9999999999999809
            }
          },
          "Description": "Destruction"
        }
      ]
    }
  ]
}