{
  "Name": "MERBM_spm_hig_1_A_std_15",
  "GeneralInformation": {
    "ID": "string",
    "Description": "string",
    "Building type": "string",
    "Roof Shape": "string",
    "Roof Cover Type": "string",
    "Roof Cover Quality": "string",
    "Roof Deck Attachment": "string",
    "Roof-Wall Connection": "string",
    "Secondary Water Resistance": "bool",
    "Garage": "string",
    "Shutters": "bool",
    "Terrain": "string"
  },
  "EDP": {
    "Type": "Peak Gust Wind Speed",
    "Unit": [
      1.0,
      "mph"
    ]
  },
  "DSGroups": [
    {
      "MedianEDP": 104.8715352226848,
      "Beta": 0.1596947679265392,
      "CurveType": "LogNormal",
      "DSGroupType": "Single",
      "DamageStates": [
        {
          "Weight": 1.0,
          "Consequences": {
            "ReconstructionCost": {
              "Amount": 0.028653668985455058
            }
          },
          "Description": "Minor"
        }
      ]
    },
    {
      "MedianEDP": 114.2798429332231,
      "Beta": 0.13239079689097877,
      "CurveType": "LogNormal",
      "DSGroupType": "Single",
      "DamageStates": [
        {
          "Weight": 1.0,
          "Consequences": {
            "ReconstructionCost": {
              "Amount": 0.054269446206906484
            }
          },
          "Description": "Moderate"
        }
      ]
    },
    {
      "MedianEDP": 161.87346435635385,
      "Beta": 0.08447268084723356,
      "CurveType": "LogNormal",
      "DSGroupType": "Single",
      "DamageStates": [
        {
          "Weight": 1.0,
          "Consequences": {
            "ReconstructionCost": {
              "Amount": 0.3428869383200012
            }
          },
          "Description": "Severe"
        }
      ]
    },
    {
      "MedianEDP": 186.51646839469987,
      "Beta": 0.12515753042236763,
      "CurveType": "LogNormal",
      "DSGroupType": "Single",
      "DamageStates": [
        {
          "Weight": 1.0,
          "Consequences": {
            "ReconstructionCost": {
              "Amount": 0.5334277281994658
            }
          },
          "Description": "Destruction"
        }
      ]
    }
  ]
}