{
  "Name": "MLRM1_bur_6d_nav_trs_tnail_1_B_0_nav_75",
  "GeneralInformation": {
    "ID": "string",
    "Description": "string",
    "Building type": "string",
    "Roof Shape": "string",
    "Roof Cover Type": "string",
    "Roof Cover Quality": "string",
    "Roof Deck Attachment": "string",
    "Roof-Wall Connection": "string",
    "Secondary Water Resistance": "bool",
    "Garage": "string",
    "Shutters": "bool",
    "Terrain": "string"
  },
  "EDP": {
    "Type": "Peak Gust Wind Speed",
    "Unit": [
      1.0,
      "mph"
    ]
  },
  "DSGroups": [
    {
      "MedianEDP": 137.86478078637552,
      "Beta": 0.17821477659548685,
      "CurveType": "LogNormal",
      "DSGroupType": "Single",
      "DamageStates": [
        {
          "Weight": 1.0,
          "Consequences": {
            "ReconstructionCost": {
              "Amount": 0.047679730676060586
            }
          },
          "Description": "Minor"
        }
      ]
    },
    {
      "MedianEDP": 151.07092118106078,
      "Beta": 0.1426886550313362,
      "CurveType": "LogNormal",
      "DSGroupType": "Single",
      "DamageStates": [
        {
          "Weight": 1.0,
          "Consequences": {
            "ReconstructionCost": {
              "Amount": 0.1524128994629852
            }
          },
          "Description": "Moderate"
        }
      ]
    },
    {
      "MedianEDP": 169.01442754610696,
      "Beta": 0.12505923954262949,
      "CurveType": "LogNormal",
      "DSGroupType": "Single",
      "DamageStates": [
        {
          "Weight": 1.0,
          "Consequences": {
            "ReconstructionCost": {
              "Amount": 0.4055945778101083
            }
          },
          "Description": "Severe"
        }
      ]
    },
    {
      "MedianEDP": 187.09522923713018,
      "Beta": 0.11699708890584666,
      "CurveType": "LogNormal",
      "DSGroupType": "Single",
      "DamageStates": [
        {
          "Weight": 1.0,
          "Consequences": {
            "ReconstructionCost": {
              "Amount": 0.6822487593070263
            }
          },
          "Description": "Destruction"
        }
      ]
    }
  ]
}