{
  "Name": "MLRM2_spm_8s_nav_trs_0_strap_0_C_nav_0_nav_35",
  "GeneralInformation": {
    "ID": "string",
    "Description": "string",
    "Building type": "string",
    "Roof Shape": "string",
    "Roof Cover Type": "string",
    "Roof Cover Quality": "string",
    "Roof Deck Attachment": "string",
    "Roof-Wall Connection": "string",
    "Secondary Water Resistance": "bool",
    "Garage": "string",
    "Shutters": "bool",
    "Terrain": "string"
  },
  "EDP": {
    "Type": "Peak Gust Wind Speed",
    "Unit": [
      1.0,
      "mph"
    ]
  },
  "DSGroups": [
    {
      "MedianEDP": 126.68897279133854,
      "Beta": 0.16230590240173115,
      "CurveType": "LogNormal",
      "DSGroupType": "Single",
      "DamageStates": [
        {
          "Weight": 1.0,
          "Consequences": {
            "ReconstructionCost": {
              "Amount": 0.06121270060868898
            }
          },
          "Description": "Minor"
        }
      ]
    },
    {
      "MedianEDP": 136.50268198744158,
      "Beta": 0.12893627496396792,
      "CurveType": "LogNormal",
      "DSGroupType": "Single",
      "DamageStates": [
        {
          "Weight": 1.0,
          "Consequences": {
            "ReconstructionCost": {
              "Amount": 0.18322668071733156
            }
          },
          "Description": "Moderate"
        }
      ]
    },
    {
      "MedianEDP": 144.17632690994668,
      "Beta": 0.11734340063492195,
      "CurveType": "LogNormal",
      "DSGroupType": "Single",
      "DamageStates": [
        {
          "Weight": 1.0,
          "Consequences": {
            "ReconstructionCost": {
              "Amount": 0.33256032191190776
            }
          },
          "Description": "Severe"
        }
      ]
    },
    {
      "MedianEDP": 153.66622653343623,
      "Beta": 0.10607320503186202,
      "CurveType": "LogNormal",
      "DSGroupType": "Single",
      "DamageStates": [
        {
          "Weight": 1.0,
          "Consequences": {
            "ReconstructionCost": {
              "Amount": 0.5458852393029854
            }
          },
          "Description": "Destruction"
        }
      ]
    }
  ]
}