{
  "Name": "MLRM2_bur_6d_nav_trs_0_strap_1_D_nav_0_nav_15",
  "GeneralInformation": {
    "ID": "string",
    "Description": "string",
    "Building type": "string",
    "Roof Shape": "string",
    "Roof Cover Type": "string",
    "Roof Cover Quality": "string",
    "Roof Deck Attachment": "string",
    "Roof-Wall Connection": "string",
    "Secondary Water Resistance": "bool",
    "Garage": "string",
    "Shutters": "bool",
    "Terrain": "string"
  },
  "EDP": {
    "Type": "Peak Gust Wind Speed",
    "Unit": [
      1.0,
      "mph"
    ]
  },
  "DSGroups": [
    {
      "MedianEDP": 110.40613750448958,
      "Beta": 0.18169574967021618,
      "CurveType": "LogNormal",
      "DSGroupType": "Single",
      "DamageStates": [
        {
          "Weight": 1.0,
          "Consequences": {
            "ReconstructionCost": {
              "Amount": 0.02800192434488939
            }
          },
          "Description": "Minor"
        }
      ]
    },
    {
      "MedianEDP": 120.64253776499002,
      "Beta": 0.15094595180713757,
      "CurveType": "LogNormal",
      "DSGroupType": "Single",
      "DamageStates": [
        {
          "Weight": 1.0,
          "Consequences": {
            "ReconstructionCost": {
              "Amount": 0.09286908766579288
            }
          },
          "Description": "Moderate"
        }
      ]
    },
    {
      "MedianEDP": 134.02500000436828,
      "Beta": 0.1374089564033903,
      "CurveType": "LogNormal",
      "DSGroupType": "Single",
      "DamageStates": [
        {
          "Weight": 1.0,
          "Consequences": {
            "ReconstructionCost": {
              "Amount": 0.2656496523290034
            }
          },
          "Description": "Severe"
        }
      ]
    },
    {
      "MedianEDP": 160.5976436500015,
      "Beta": 0.10668301609647149,
      "CurveType": "LogNormal",
      "DSGroupType": "Single",
      "DamageStates": [
        {
          "Weight": 1.0,
          "Consequences": {
            "ReconstructionCost": {
              "Amount": 0.7166402548002397
            }
          },
          "Description": "Destruction"
        }
      ]
    }
  ]
}