{
  "Name": "MLRM1_spm_8s_nav_trs_strap_1_B_1_nav_3",
  "GeneralInformation": {
    "ID": "string",
    "Description": "string",
    "Building type": "string",
    "Roof Shape": "string",
    "Roof Cover Type": "string",
    "Roof Cover Quality": "string",
    "Roof Deck Attachment": "string",
    "Roof-Wall Connection": "string",
    "Secondary Water Resistance": "bool",
    "Garage": "string",
    "Shutters": "bool",
    "Terrain": "string"
  },
  "EDP": {
    "Type": "Peak Gust Wind Speed",
    "Unit": [
      1.0,
      "mph"
    ]
  },
  "DSGroups": [
    {
      "MedianEDP": 136.0072492649722,
      "Beta": 0.18163197155766736,
      "CurveType": "LogNormal",
      "DSGroupType": "Single",
      "DamageStates": [
        {
          "Weight": 1.0,
          "Consequences": {
            "ReconstructionCost": {
              "Amount": 0.04305304131520281
            }
          },
          "Description": "Minor"
        }
      ]
    },
    {
      "MedianEDP": 150.30504919250805,
      "Beta": 0.16607627479778214,
      "CurveType": "LogNormal",
      "DSGroupType": "Single",
      "DamageStates": [
        {
          "Weight": 1.0,
          "Consequences": {
            "ReconstructionCost": {
              "Amount": 0.11703387936255505
            }
          },
          "Description": "Moderate"
        }
      ]
    },
    {
      "MedianEDP": 173.50891397452074,
      "Beta": 0.14637422714522255,
      "CurveType": "LogNormal",
      "DSGroupType": "Single",
      "DamageStates": [
        {
          "Weight": 1.0,
          "Consequences": {
            "ReconstructionCost": {
              "Amount": 0.3321515600588346
            }
          },
          "Description": "Severe"
        }
      ]
    },
    {
      "MedianEDP": 203.5419562315597,
      "Beta": 0.11878129271924273,
      "CurveType": "LogNormal",
      "DSGroupType": "Single",
      "DamageStates": [
        {
          "Weight": 1.0,
          "Consequences": {
            "ReconstructionCost": {
              "Amount": 0.6578731681681798
            }
          },
          "Description": "Destruction"
        }
      ]
    }
  ]
}