{
  "Name": "MLRM1_bur_8d_nav_trs_tnail_1_D_1_nav_3",
  "GeneralInformation": {
    "ID": "string",
    "Description": "string",
    "Building type": "string",
    "Roof Shape": "string",
    "Roof Cover Type": "string",
    "Roof Cover Quality": "string",
    "Roof Deck Attachment": "string",
    "Roof-Wall Connection": "string",
    "Secondary Water Resistance": "bool",
    "Garage": "string",
    "Shutters": "bool",
    "Terrain": "string"
  },
  "EDP": {
    "Type": "Peak Gust Wind Speed",
    "Unit": [
      1.0,
      "mph"
    ]
  },
  "DSGroups": [
    {
      "MedianEDP": 117.22972258221533,
      "Beta": 0.19163935629792833,
      "CurveType": "LogNormal",
      "DSGroupType": "Single",
      "DamageStates": [
        {
          "Weight": 1.0,
          "Consequences": {
            "ReconstructionCost": {
              "Amount": 0.04733217579943697
            }
          },
          "Description": "Minor"
        }
      ]
    },
    {
      "MedianEDP": 132.7642524801988,
      "Beta": 0.15915115778516348,
      "CurveType": "LogNormal",
      "DSGroupType": "Single",
      "DamageStates": [
        {
          "Weight": 1.0,
          "Consequences": {
            "ReconstructionCost": {
              "Amount": 0.17272514832561714
            }
          },
          "Description": "Moderate"
        }
      ]
    },
    {
      "MedianEDP": 148.13050286013456,
      "Beta": 0.13203778493324542,
      "CurveType": "LogNormal",
      "DSGroupType": "Single",
      "DamageStates": [
        {
          "Weight": 1.0,
          "Consequences": {
            "ReconstructionCost": {
              "Amount": 0.3809894574852973
            }
          },
          "Description": "Severe"
        }
      ]
    },
    {
      "MedianEDP": 164.59415087912285,
      "Beta": 0.12802904335347448,
      "CurveType": "LogNormal",
      "DSGroupType": "Single",
      "DamageStates": [
        {
          "Weight": 1.0,
          "Consequences": {
            "ReconstructionCost": {
              "Amount": 0.6230614203214011
            }
          },
          "Description": "Destruction"
        }
      ]
    }
  ]
}