{
  "Name": "MLRM1_spm_8d_nav_trs_strap_0_A_0_nav_3",
  "GeneralInformation": {
    "ID": "string",
    "Description": "string",
    "Building type": "string",
    "Roof Shape": "string",
    "Roof Cover Type": "string",
    "Roof Cover Quality": "string",
    "Roof Deck Attachment": "string",
    "Roof-Wall Connection": "string",
    "Secondary Water Resistance": "bool",
    "Garage": "string",
    "Shutters": "bool",
    "Terrain": "string"
  },
  "EDP": {
    "Type": "Peak Gust Wind Speed",
    "Unit": [
      1.0,
      "mph"
    ]
  },
  "DSGroups": [
    {
      "MedianEDP": 104.42726087626218,
      "Beta": 0.18347798063157822,
      "CurveType": "LogNormal",
      "DSGroupType": "Single",
      "DamageStates": [
        {
          "Weight": 1.0,
          "Consequences": {
            "ReconstructionCost": {
              "Amount": 0.0179929551785006
            }
          },
          "Description": "Minor"
        }
      ]
    },
    {
      "MedianEDP": 115.61152219918338,
      "Beta": 0.17230550028577446,
      "CurveType": "LogNormal",
      "DSGroupType": "Single",
      "DamageStates": [
        {
          "Weight": 1.0,
          "Consequences": {
            "ReconstructionCost": {
              "Amount": 0.07808560743980862
            }
          },
          "Description": "Moderate"
        }
      ]
    },
    {
      "MedianEDP": 133.22965823556538,
      "Beta": 0.14745108483537434,
      "CurveType": "LogNormal",
      "DSGroupType": "Single",
      "DamageStates": [
        {
          "Weight": 1.0,
          "Consequences": {
            "ReconstructionCost": {
              "Amount": 0.3186523209162727
            }
          },
          "Description": "Severe"
        }
      ]
    },
    {
      "MedianEDP": 153.0429254029403,
      "Beta": 0.12451836696595557,
      "CurveType": "LogNormal",
      "DSGroupType": "Single",
      "DamageStates": [
        {
          "Weight": 1.0,
          "Consequences": {
            "ReconstructionCost": {
              "Amount": 0.6750153393861844
            }
          },
          "Description": "Destruction"
        }
      ]
    }
  ]
}