{
  "Name": "MLRM2_bur_6s_nav_trs_0_strap_1_C_nav_1_nav_15",
  "GeneralInformation": {
    "ID": "string",
    "Description": "string",
    "Building type": "string",
    "Roof Shape": "string",
    "Roof Cover Type": "string",
    "Roof Cover Quality": "string",
    "Roof Deck Attachment": "string",
    "Roof-Wall Connection": "string",
    "Secondary Water Resistance": "bool",
    "Garage": "string",
    "Shutters": "bool",
    "Terrain": "string"
  },
  "EDP": {
    "Type": "Peak Gust Wind Speed",
    "Unit": [
      1.0,
      "mph"
    ]
  },
  "DSGroups": [
    {
      "MedianEDP": 132.4321195470288,
      "Beta": 0.17357318132679211,
      "CurveType": "LogNormal",
      "DSGroupType": "Single",
      "DamageStates": [
        {
          "Weight": 1.0,
          "Consequences": {
            "ReconstructionCost": {
              "Amount": 0.08220229662769846
            }
          },
          "Description": "Minor"
        }
      ]
    },
    {
      "MedianEDP": 148.5632723763332,
      "Beta": 0.14332015129050674,
      "CurveType": "LogNormal",
      "DSGroupType": "Single",
      "DamageStates": [
        {
          "Weight": 1.0,
          "Consequences": {
            "ReconstructionCost": {
              "Amount": 0.24156811498779573
            }
          },
          "Description": "Moderate"
        }
      ]
    },
    {
      "MedianEDP": 161.76347000107629,
      "Beta": 0.15880522504918185,
      "CurveType": "LogNormal",
      "DSGroupType": "Single",
      "DamageStates": [
        {
          "Weight": 1.0,
          "Consequences": {
            "ReconstructionCost": {
              "Amount": 0.4243044397758979
            }
          },
          "Description": "Severe"
        }
      ]
    },
    {
      "MedianEDP": 185.49098727568443,
      "Beta": 0.17356786637165894,
      "CurveType": "LogNormal",
      "DSGroupType": "Single",
      "DamageStates": [
        {
          "Weight": 1.0,
          "Consequences": {
            "ReconstructionCost": {
              "Amount": 0.7355659152389545
            }
          },
          "Description": "Destruction"
        }
      ]
    }
  ]
}