{
  "Name": "MLRM1_bur_6d_god_ows_tnail_1_B_1_std_15",
  "GeneralInformation": {
    "ID": "string",
    "Description": "string",
    "Building type": "string",
    "Roof Shape": "string",
    "Roof Cover Type": "string",
    "Roof Cover Quality": "string",
    "Roof Deck Attachment": "string",
    "Roof-Wall Connection": "string",
    "Secondary Water Resistance": "bool",
    "Garage": "string",
    "Shutters": "bool",
    "Terrain": "string"
  },
  "EDP": {
    "Type": "Peak Gust Wind Speed",
    "Unit": [
      1.0,
      "mph"
    ]
  },
  "DSGroups": [
    {
      "MedianEDP": 124.8712155095267,
      "Beta": 0.18287965890984198,
      "CurveType": "LogNormal",
      "DSGroupType": "Single",
      "DamageStates": [
        {
          "Weight": 1.0,
          "Consequences": {
            "ReconstructionCost": {
              "Amount": 0.04482369839727239
            }
          },
          "Description": "Minor"
        }
      ]
    },
    {
      "MedianEDP": 144.715305212673,
      "Beta": 0.16436980149908803,
      "CurveType": "LogNormal",
      "DSGroupType": "Single",
      "DamageStates": [
        {
          "Weight": 1.0,
          "Consequences": {
            "ReconstructionCost": {
              "Amount": 0.10048431463769514
            }
          },
          "Description": "Moderate"
        }
      ]
    },
    {
      "MedianEDP": 175.3085913414902,
      "Beta": 0.17013507060169303,
      "CurveType": "LogNormal",
      "DSGroupType": "Single",
      "DamageStates": [
        {
          "Weight": 1.0,
          "Consequences": {
            "ReconstructionCost": {
              "Amount": 0.23127428210190198
            }
          },
          "Description": "Severe"
        }
      ]
    },
    {
      "MedianEDP": 249.7123666407313,
      "Beta": 0.1645744902313886,
      "CurveType": "LogNormal",
      "DSGroupType": "Single",
      "DamageStates": [
        {
          "Weight": 1.0,
          "Consequences": {
            "ReconstructionCost": {
              "Amount": 0.6060659151232297
            }
          },
          "Description": "Destruction"
        }
      ]
    }
  ]
}