{
  "Name": "MLRM2_bur_6d_nav_trs_0_strap_1_B_nav_1_nav_100",
  "GeneralInformation": {
    "ID": "string",
    "Description": "string",
    "Building type": "string",
    "Roof Shape": "string",
    "Roof Cover Type": "string",
    "Roof Cover Quality": "string",
    "Roof Deck Attachment": "string",
    "Roof-Wall Connection": "string",
    "Secondary Water Resistance": "bool",
    "Garage": "string",
    "Shutters": "bool",
    "Terrain": "string"
  },
  "EDP": {
    "Type": "Peak Gust Wind Speed",
    "Unit": [
      1.0,
      "mph"
    ]
  },
  "DSGroups": [
    {
      "MedianEDP": 122.92526611749625,
      "Beta": 0.18212782956365114,
      "CurveType": "LogNormal",
      "DSGroupType": "Single",
      "DamageStates": [
        {
          "Weight": 1.0,
          "Consequences": {
            "ReconstructionCost": {
              "Amount": 0.036484433001170304
            }
          },
          "Description": "Minor"
        }
      ]
    },
    {
      "MedianEDP": 134.76650827877276,
      "Beta": 0.1490267140992217,
      "CurveType": "LogNormal",
      "DSGroupType": "Single",
      "DamageStates": [
        {
          "Weight": 1.0,
          "Consequences": {
            "ReconstructionCost": {
              "Amount": 0.09858511766918121
            }
          },
          "Description": "Moderate"
        }
      ]
    },
    {
      "MedianEDP": 151.65384534517443,
      "Beta": 0.14097576187753028,
      "CurveType": "LogNormal",
      "DSGroupType": "Single",
      "DamageStates": [
        {
          "Weight": 1.0,
          "Consequences": {
            "ReconstructionCost": {
              "Amount": 0.2599539818570139
            }
          },
          "Description": "Severe"
        }
      ]
    },
    {
      "MedianEDP": 205.83137018967042,
      "Beta": 0.13050496816521584,
      "CurveType": "LogNormal",
      "DSGroupType": "Single",
      "DamageStates": [
        {
          "Weight": 1.0,
          "Consequences": {
            "ReconstructionCost": {
              "Amount": 0.8481164395871881
            }
          },
          "Description": "Destruction"
        }
      ]
    }
  ]
}