{
  "Name": "MMUH1_flt_1_bur_por_6d_tnail_1_0_35",
  "GeneralInformation": {
    "ID": "string",
    "Description": "string",
    "Building type": "string",
    "Roof Shape": "string",
    "Roof Cover Type": "string",
    "Roof Cover Quality": "string",
    "Roof Deck Attachment": "string",
    "Roof-Wall Connection": "string",
    "Secondary Water Resistance": "bool",
    "Garage": "string",
    "Shutters": "bool",
    "Terrain": "string"
  },
  "EDP": {
    "Type": "Peak Gust Wind Speed",
    "Unit": [
      1.0,
      "mph"
    ]
  },
  "DSGroups": [
    {
      "MedianEDP": 114.94789963731957,
      "Beta": 0.19323185271588045,
      "CurveType": "LogNormal",
      "DSGroupType": "Single",
      "DamageStates": [
        {
          "Weight": 1.0,
          "Consequences": {
            "ReconstructionCost": {
              "Amount": 0.03726407870625152
            }
          },
          "Description": "Minor"
        }
      ]
    },
    {
      "MedianEDP": 129.30703875896378,
      "Beta": 0.16789585191138034,
      "CurveType": "LogNormal",
      "DSGroupType": "Single",
      "DamageStates": [
        {
          "Weight": 1.0,
          "Consequences": {
            "ReconstructionCost": {
              "Amount": 0.0958516279487649
            }
          },
          "Description": "Moderate"
        }
      ]
    },
    {
      "MedianEDP": 159.76510769558797,
      "Beta": 0.1463216240626114,
      "CurveType": "LogNormal",
      "DSGroupType": "Single",
      "DamageStates": [
        {
          "Weight": 1.0,
          "Consequences": {
            "ReconstructionCost": {
              "Amount": 0.3274391423363485
            }
          },
          "Description": "Severe"
        }
      ]
    },
    {
      "MedianEDP": 204.64872486483654,
      "Beta": 0.13955176629176735,
      "CurveType": "LogNormal",
      "DSGroupType": "Single",
      "DamageStates": [
        {
          "Weight": 1.0,
          "Consequences": {
            "ReconstructionCost": {
              "Amount": 0.7115776956458321
            }
          },
          "Description": "Destruction"
        }
      ]
    }
  ]
}