{
  "Name": "MMUH1_flt_1_bur_por_6d_tnail_0_1_35",
  "GeneralInformation": {
    "ID": "string",
    "Description": "string",
    "Building type": "string",
    "Roof Shape": "string",
    "Roof Cover Type": "string",
    "Roof Cover Quality": "string",
    "Roof Deck Attachment": "string",
    "Roof-Wall Connection": "string",
    "Secondary Water Resistance": "bool",
    "Garage": "string",
    "Shutters": "bool",
    "Terrain": "string"
  },
  "EDP": {
    "Type": "Peak Gust Wind Speed",
    "Unit": [
      1.0,
      "mph"
    ]
  },
  "DSGroups": [
    {
      "MedianEDP": 112.12205683834823,
      "Beta": 0.18052292364445743,
      "CurveType": "LogNormal",
      "DSGroupType": "Single",
      "DamageStates": [
        {
          "Weight": 1.0,
          "Consequences": {
            "ReconstructionCost": {
              "Amount": 0.02993062828696867
            }
          },
          "Description": "Minor"
        }
      ]
    },
    {
      "MedianEDP": 126.84761025689173,
      "Beta": 0.1583258121184054,
      "CurveType": "LogNormal",
      "DSGroupType": "Single",
      "DamageStates": [
        {
          "Weight": 1.0,
          "Consequences": {
            "ReconstructionCost": {
              "Amount": 0.09539518794173762
            }
          },
          "Description": "Moderate"
        }
      ]
    },
    {
      "MedianEDP": 154.56509290580755,
      "Beta": 0.13853321562120455,
      "CurveType": "LogNormal",
      "DSGroupType": "Single",
      "DamageStates": [
        {
          "Weight": 1.0,
          "Consequences": {
            "ReconstructionCost": {
              "Amount": 0.3484001890827798
            }
          },
          "Description": "Severe"
        }
      ]
    },
    {
      "MedianEDP": 183.5018342463261,
      "Beta": 0.12328065777261708,
      "CurveType": "LogNormal",
      "DSGroupType": "Single",
      "DamageStates": [
        {
          "Weight": 1.0,
          "Consequences": {
            "ReconstructionCost": {
              "Amount": 0.6583691688894014
            }
          },
          "Description": "Destruction"
        }
      ]
    }
  ]
}