{
  "Name": "MMUH3_flt_1_spm_por_8d_strap_1_1_15",
  "GeneralInformation": {
    "ID": "string",
    "Description": "string",
    "Building type": "string",
    "Roof Shape": "string",
    "Roof Cover Type": "string",
    "Roof Cover Quality": "string",
    "Roof Deck Attachment": "string",
    "Roof-Wall Connection": "string",
    "Secondary Water Resistance": "bool",
    "Garage": "string",
    "Shutters": "bool",
    "Terrain": "string"
  },
  "EDP": {
    "Type": "Peak Gust Wind Speed",
    "Unit": [
      1.0,
      "mph"
    ]
  },
  "DSGroups": [
    {
      "MedianEDP": 99.82939620504075,
      "Beta": 0.22271862982621313,
      "CurveType": "LogNormal",
      "DSGroupType": "Single",
      "DamageStates": [
        {
          "Weight": 1.0,
          "Consequences": {
            "ReconstructionCost": {
              "Amount": 0.12834985783732006
            }
          },
          "Description": "Minor"
        }
      ]
    },
    {
      "MedianEDP": 103.73029727608892,
      "Beta": 0.2093092898069881,
      "CurveType": "LogNormal",
      "DSGroupType": "Single",
      "DamageStates": [
        {
          "Weight": 1.0,
          "Consequences": {
            "ReconstructionCost": {
              "Amount": 0.15171912931127002
            }
          },
          "Description": "Moderate"
        }
      ]
    },
    {
      "MedianEDP": 116.53506049957453,
      "Beta": 0.1895088766561821,
      "CurveType": "LogNormal",
      "DSGroupType": "Single",
      "DamageStates": [
        {
          "Weight": 1.0,
          "Consequences": {
            "ReconstructionCost": {
              "Amount": 0.23890628060032
            }
          },
          "Description": "Severe"
        }
      ]
    },
    {
      "MedianEDP": 245.12592452165373,
      "Beta": 0.12162307351955118,
      "CurveType": "LogNormal",
      "DSGroupType": "Single",
      "DamageStates": [
        {
          "Weight": 1.0,
          "Consequences": {
            "ReconstructionCost": {
              "Amount": 0.908192840699113
            }
          },
          "Description": "Destruction"
        }
      ]
    }
  ]
}