{
  "Name": "MMUH1_gab_1_nav_nav_8d_tnail_1_0_100",
  "GeneralInformation": {
    "ID": "string",
    "Description": "string",
    "Building type": "string",
    "Roof Shape": "string",
    "Roof Cover Type": "string",
    "Roof Cover Quality": "string",
    "Roof Deck Attachment": "string",
    "Roof-Wall Connection": "string",
    "Secondary Water Resistance": "bool",
    "Garage": "string",
    "Shutters": "bool",
    "Terrain": "string"
  },
  "EDP": {
    "Type": "Peak Gust Wind Speed",
    "Unit": [
      1.0,
      "mph"
    ]
  },
  "DSGroups": [
    {
      "MedianEDP": 122.32462584280377,
      "Beta": 0.13695454964252315,
      "CurveType": "LogNormal",
      "DSGroupType": "Single",
      "DamageStates": [
        {
          "Weight": 1.0,
          "Consequences": {
            "ReconstructionCost": {
              "Amount": 0.004599517381824969
            }
          },
          "Description": "Minor"
        }
      ]
    },
    {
      "MedianEDP": 152.55151786516237,
      "Beta": 0.13044495591881483,
      "CurveType": "LogNormal",
      "DSGroupType": "Single",
      "DamageStates": [
        {
          "Weight": 1.0,
          "Consequences": {
            "ReconstructionCost": {
              "Amount": 0.10255642091880901
            }
          },
          "Description": "Moderate"
        }
      ]
    },
    {
      "MedianEDP": 175.70182540525988,
      "Beta": 0.10991168751198865,
      "CurveType": "LogNormal",
      "DSGroupType": "Single",
      "DamageStates": [
        {
          "Weight": 1.0,
          "Consequences": {
            "ReconstructionCost": {
              "Amount": 0.34038892519453834
            }
          },
          "Description": "Severe"
        }
      ]
    },
    {
      "MedianEDP": 187.03146746081237,
      "Beta": 0.1216841634939555,
      "CurveType": "LogNormal",
      "DSGroupType": "Single",
      "DamageStates": [
        {
          "Weight": 1.0,
          "Consequences": {
            "ReconstructionCost": {
              "Amount": 0.48686425186862414
            }
          },
          "Description": "Destruction"
        }
      ]
    }
  ]
}