{
  "Name": "MSF1_hip_1_6d_tnail_nav_0_0_15",
  "GeneralInformation": {
    "ID": "string",
    "Description": "string",
    "Building type": "string",
    "Roof Shape": "string",
    "Roof Cover Type": "string",
    "Roof Cover Quality": "string",
    "Roof Deck Attachment": "string",
    "Roof-Wall Connection": "string",
    "Secondary Water Resistance": "bool",
    "Garage": "string",
    "Shutters": "bool",
    "Terrain": "string"
  },
  "EDP": {
    "Type": "Peak Gust Wind Speed",
    "Unit": [
      1.0,
      "mph"
    ]
  },
  "DSGroups": [
    {
      "MedianEDP": 108.69469430405742,
      "Beta": 0.1294267758796098,
      "CurveType": "LogNormal",
      "DSGroupType": "Single",
      "DamageStates": [
        {
          "Weight": 1.0,
          "Consequences": {
            "ReconstructionCost": {
              "Amount": 0.03525270631212116
            }
          },
          "Description": "Minor"
        }
      ]
    },
    {
      "MedianEDP": 127.26838721387993,
      "Beta": 0.10913635134303279,
      "CurveType": "LogNormal",
      "DSGroupType": "Single",
      "DamageStates": [
        {
          "Weight": 1.0,
          "Consequences": {
            "ReconstructionCost": {
              "Amount": 0.2780674978440924
            }
          },
          "Description": "Moderate"
        }
      ]
    },
    {
      "MedianEDP": 139.48552963186413,
      "Beta": 0.0965045382883074,
      "CurveType": "LogNormal",
      "DSGroupType": "Single",
      "DamageStates": [
        {
          "Weight": 1.0,
          "Consequences": {
            "ReconstructionCost": {
              "Amount": 0.5478834160503435
            }
          },
          "Description": "Severe"
        }
      ]
    },
    {
      "MedianEDP": 143.7917435021741,
      "Beta": 0.1078362799275571,
      "CurveType": "LogNormal",
      "DSGroupType": "Single",
      "DamageStates": [
        {
          "Weight": 1.0,
          "Consequences": {
            "ReconstructionCost": {
              "Amount": 0.6388794207717337
            }
          },
          "Description": "Destruction"
        }
      ]
    }
  ]
}