{
  "Name": "MSF1_gab_0_tnail_0rcshl_su_75",
  "GeneralInformation": {
    "ID": "string",
    "Description": "string",
    "Building type": "string",
    "Roof Shape": "string",
    "Roof Cover Type": "string",
    "Roof Cover Quality": "string",
    "Roof Deck Attachment": "string",
    "Roof-Wall Connection": "string",
    "Secondary Water Resistance": "bool",
    "Garage": "string",
    "Shutters": "bool",
    "Terrain": "string"
  },
  "EDP": {
    "Type": "Peak Gust Wind Speed",
    "Unit": [
      1.0,
      "mph"
    ]
  },
  "DSGroups": [
    {
      "MedianEDP": 135.20065514946816,
      "Beta": 0.12846034660088038,
      "CurveType": "LogNormal",
      "DSGroupType": "Single",
      "DamageStates": [
        {
          "Weight": 1.0,
          "Consequences": {
            "ReconstructionCost": {
              "Amount": 0.07015419168236528
            }
          },
          "Description": "Minor"
        }
      ]
    },
    {
      "MedianEDP": 156.99443816806826,
      "Beta": 0.1132250567395981,
      "CurveType": "LogNormal",
      "DSGroupType": "Single",
      "DamageStates": [
        {
          "Weight": 1.0,
          "Consequences": {
            "ReconstructionCost": {
              "Amount": 0.36959271566281887
            }
          },
          "Description": "Moderate"
        }
      ]
    },
    {
      "MedianEDP": 166.08264587294204,
      "Beta": 0.1145712073484056,
      "CurveType": "LogNormal",
      "DSGroupType": "Single",
      "DamageStates": [
        {
          "Weight": 1.0,
          "Consequences": {
            "ReconstructionCost": {
              "Amount": 0.5386273672871217
            }
          },
          "Description": "Severe"
        }
      ]
    },
    {
      "MedianEDP": 168.23050792723666,
      "Beta": 0.12137958073318339,
      "CurveType": "LogNormal",
      "DSGroupType": "Single",
      "DamageStates": [
        {
          "Weight": 1.0,
          "Consequences": {
            "ReconstructionCost": {
              "Amount": 0.5773580625326304
            }
          },
          "Description": "Destruction"
        }
      ]
    }
  ]
}