{
  "Name": "MSF2_gab_0_8s_tnail_nav_1_0_35",
  "GeneralInformation": {
    "ID": "string",
    "Description": "string",
    "Building type": "string",
    "Roof Shape": "string",
    "Roof Cover Type": "string",
    "Roof Cover Quality": "string",
    "Roof Deck Attachment": "string",
    "Roof-Wall Connection": "string",
    "Secondary Water Resistance": "bool",
    "Garage": "string",
    "Shutters": "bool",
    "Terrain": "string"
  },
  "EDP": {
    "Type": "Peak Gust Wind Speed",
    "Unit": [
      1.0,
      "mph"
    ]
  },
  "DSGroups": [
    {
      "MedianEDP": 116.95284484197308,
      "Beta": 0.13713890817281463,
      "CurveType": "LogNormal",
      "DSGroupType": "Single",
      "DamageStates": [
        {
          "Weight": 1.0,
          "Consequences": {
            "ReconstructionCost": {
              "Amount": 0.023610411348441926
            }
          },
          "Description": "Minor"
        }
      ]
    },
    {
      "MedianEDP": 141.56712878624992,
      "Beta": 0.12464961260765968,
      "CurveType": "LogNormal",
      "DSGroupType": "Single",
      "DamageStates": [
        {
          "Weight": 1.0,
          "Consequences": {
            "ReconstructionCost": {
              "Amount": 0.3180966634772575
            }
          },
          "Description": "Moderate"
        }
      ]
    },
    {
      "MedianEDP": 153.21882919497557,
      "Beta": 0.10960261872282612,
      "CurveType": "LogNormal",
      "DSGroupType": "Single",
      "DamageStates": [
        {
          "Weight": 1.0,
          "Consequences": {
            "ReconstructionCost": {
              "Amount": 0.5607163768978286
            }
          },
          "Description": "Severe"
        }
      ]
    },
    {
      "MedianEDP": 155.5724181149982,
      "Beta": 0.11358510949773734,
      "CurveType": "LogNormal",
      "DSGroupType": "Single",
      "DamageStates": [
        {
          "Weight": 1.0,
          "Consequences": {
            "ReconstructionCost": {
              "Amount": 0.6077283515299295
            }
          },
          "Description": "Destruction"
        }
      ]
    }
  ]
}