{
  "Name": "MSF2_hip_1_8d_tnail_nav_0_1_15",
  "GeneralInformation": {
    "ID": "string",
    "Description": "string",
    "Building type": "string",
    "Roof Shape": "string",
    "Roof Cover Type": "string",
    "Roof Cover Quality": "string",
    "Roof Deck Attachment": "string",
    "Roof-Wall Connection": "string",
    "Secondary Water Resistance": "bool",
    "Garage": "string",
    "Shutters": "bool",
    "Terrain": "string"
  },
  "EDP": {
    "Type": "Peak Gust Wind Speed",
    "Unit": [
      1.0,
      "mph"
    ]
  },
  "DSGroups": [
    {
      "MedianEDP": 99.44003789827343,
      "Beta": 0.13210969282539198,
      "CurveType": "LogNormal",
      "DSGroupType": "Single",
      "DamageStates": [
        {
          "Weight": 1.0,
          "Consequences": {
            "ReconstructionCost": {
              "Amount": 0.023013361588646482
            }
          },
          "Description": "Minor"
        }
      ]
    },
    {
      "MedianEDP": 117.08000171048377,
      "Beta": 0.10971400095018607,
      "CurveType": "LogNormal",
      "DSGroupType": "Single",
      "DamageStates": [
        {
          "Weight": 1.0,
          "Consequences": {
            "ReconstructionCost": {
              "Amount": 0.25825587705732306
            }
          },
          "Description": "Moderate"
        }
      ]
    },
    {
      "MedianEDP": 126.00367787417768,
      "Beta": 0.10017869925160403,
      "CurveType": "LogNormal",
      "DSGroupType": "Single",
      "DamageStates": [
        {
          "Weight": 1.0,
          "Consequences": {
            "ReconstructionCost": {
              "Amount": 0.48280573826552725
            }
          },
          "Description": "Severe"
        }
      ]
    },
    {
      "MedianEDP": 130.14098924288606,
      "Beta": 0.1130090722609372,
      "CurveType": "LogNormal",
      "DSGroupType": "Single",
      "DamageStates": [
        {
          "Weight": 1.0,
          "Consequences": {
            "ReconstructionCost": {
              "Amount": 0.5883326224873359
            }
          },
          "Description": "Destruction"
        }
      ]
    }
  ]
}