{
  "Name": "MSF2_gab_0_6s_tnail_wkd_0_1_100",
  "GeneralInformation": {
    "ID": "string",
    "Description": "string",
    "Building type": "string",
    "Roof Shape": "string",
    "Roof Cover Type": "string",
    "Roof Cover Quality": "string",
    "Roof Deck Attachment": "string",
    "Roof-Wall Connection": "string",
    "Secondary Water Resistance": "bool",
    "Garage": "string",
    "Shutters": "bool",
    "Terrain": "string"
  },
  "EDP": {
    "Type": "Peak Gust Wind Speed",
    "Unit": [
      1.0,
      "mph"
    ]
  },
  "DSGroups": [
    {
      "MedianEDP": 123.43096171888364,
      "Beta": 0.12670539700904782,
      "CurveType": "LogNormal",
      "DSGroupType": "Single",
      "DamageStates": [
        {
          "Weight": 1.0,
          "Consequences": {
            "ReconstructionCost": {
              "Amount": 0.05845736038002122
            }
          },
          "Description": "Minor"
        }
      ]
    },
    {
      "MedianEDP": 139.4360925110528,
      "Beta": 0.10855026787465956,
      "CurveType": "LogNormal",
      "DSGroupType": "Single",
      "DamageStates": [
        {
          "Weight": 1.0,
          "Consequences": {
            "ReconstructionCost": {
              "Amount": 0.2967396136934497
            }
          },
          "Description": "Moderate"
        }
      ]
    },
    {
      "MedianEDP": 146.3736921714623,
      "Beta": 0.10530122333920021,
      "CurveType": "LogNormal",
      "DSGroupType": "Single",
      "DamageStates": [
        {
          "Weight": 1.0,
          "Consequences": {
            "ReconstructionCost": {
              "Amount": 0.45145444548106123
            }
          },
          "Description": "Severe"
        }
      ]
    },
    {
      "MedianEDP": 153.85119352953694,
      "Beta": 0.11171673262706766,
      "CurveType": "LogNormal",
      "DSGroupType": "Single",
      "DamageStates": [
        {
          "Weight": 1.0,
          "Consequences": {
            "ReconstructionCost": {
              "Amount": 0.6181276311368287
            }
          },
          "Description": "Destruction"
        }
      ]
    }
  ]
}