{
  "Name": "MSF2_hip_0_6s_tnail_sup_1_1_3",
  "GeneralInformation": {
    "ID": "string",
    "Description": "string",
    "Building type": "string",
    "Roof Shape": "string",
    "Roof Cover Type": "string",
    "Roof Cover Quality": "string",
    "Roof Deck Attachment": "string",
    "Roof-Wall Connection": "string",
    "Secondary Water Resistance": "bool",
    "Garage": "string",
    "Shutters": "bool",
    "Terrain": "string"
  },
  "EDP": {
    "Type": "Peak Gust Wind Speed",
    "Unit": [
      1.0,
      "mph"
    ]
  },
  "DSGroups": [
    {
      "MedianEDP": 110.16661918788192,
      "Beta": 0.13554176499382026,
      "CurveType": "LogNormal",
      "DSGroupType": "Single",
      "DamageStates": [
        {
          "Weight": 1.0,
          "Consequences": {
            "ReconstructionCost": {
              "Amount": 0.026781896862902804
            }
          },
          "Description": "Minor"
        }
      ]
    },
    {
      "MedianEDP": 134.46990693688767,
      "Beta": 0.1262063757275152,
      "CurveType": "LogNormal",
      "DSGroupType": "Single",
      "DamageStates": [
        {
          "Weight": 1.0,
          "Consequences": {
            "ReconstructionCost": {
              "Amount": 0.29513547235858856
            }
          },
          "Description": "Moderate"
        }
      ]
    },
    {
      "MedianEDP": 149.2673956139206,
      "Beta": 0.10468211731726301,
      "CurveType": "LogNormal",
      "DSGroupType": "Single",
      "DamageStates": [
        {
          "Weight": 1.0,
          "Consequences": {
            "ReconstructionCost": {
              "Amount": 0.5755430720559404
            }
          },
          "Description": "Severe"
        }
      ]
    },
    {
      "MedianEDP": 155.82640466444798,
      "Beta": 0.0982448184425577,
      "CurveType": "LogNormal",
      "DSGroupType": "Single",
      "DamageStates": [
        {
          "Weight": 1.0,
          "Consequences": {
            "ReconstructionCost": {
              "Amount": 0.6882046916331546
            }
          },
          "Description": "Destruction"
        }
      ]
    }
  ]
}