{
  "Name": "MSF2_gab_1_6d_tnail_sup_1_0_35",
  "GeneralInformation": {
    "ID": "string",
    "Description": "string",
    "Building type": "string",
    "Roof Shape": "string",
    "Roof Cover Type": "string",
    "Roof Cover Quality": "string",
    "Roof Deck Attachment": "string",
    "Roof-Wall Connection": "string",
    "Secondary Water Resistance": "bool",
    "Garage": "string",
    "Shutters": "bool",
    "Terrain": "string"
  },
  "EDP": {
    "Type": "Peak Gust Wind Speed",
    "Unit": [
      1.0,
      "mph"
    ]
  },
  "DSGroups": [
    {
      "MedianEDP": 102.1084989263052,
      "Beta": 0.1409513340116348,
      "CurveType": "LogNormal",
      "DSGroupType": "Single",
      "DamageStates": [
        {
          "Weight": 1.0,
          "Consequences": {
            "ReconstructionCost": {
              "Amount": 0.005066087969917036
            }
          },
          "Description": "Minor"
        }
      ]
    },
    {
      "MedianEDP": 121.82437174416411,
      "Beta": 0.1305168301241884,
      "CurveType": "LogNormal",
      "DSGroupType": "Single",
      "DamageStates": [
        {
          "Weight": 1.0,
          "Consequences": {
            "ReconstructionCost": {
              "Amount": 0.08895509374831784
            }
          },
          "Description": "Moderate"
        }
      ]
    },
    {
      "MedianEDP": 141.6334141449856,
      "Beta": 0.11479812324091745,
      "CurveType": "LogNormal",
      "DSGroupType": "Single",
      "DamageStates": [
        {
          "Weight": 1.0,
          "Consequences": {
            "ReconstructionCost": {
              "Amount": 0.3810945839791038
            }
          },
          "Description": "Severe"
        }
      ]
    },
    {
      "MedianEDP": 156.42389863466474,
      "Beta": 0.11743078400101237,
      "CurveType": "LogNormal",
      "DSGroupType": "Single",
      "DamageStates": [
        {
          "Weight": 1.0,
          "Consequences": {
            "ReconstructionCost": {
              "Amount": 0.6502806041480468
            }
          },
          "Description": "Destruction"
        }
      ]
    }
  ]
}